{"text": "2022-10-03T21:10:26.142185+0300 INFO user_created\n", "record": {"elapsed": {"repr": "0:00:10.912082", "seconds": 10.912082}, "exception": null, "extra": {}, "file": {"name": "main.py", "path": "/home/mediocrity/projects/users_api/main.py"}, "function": "create_user", "level": {"icon": "ℹ️", "name": "INFO", "no": 20}, "line": 44, "message": "user_created", "module": "main", "name": "__main__", "process": {"id": 83571, "name": "MainProcess"}, "thread": {"id": 139703929607936, "name": "Thread-1"}, "time": {"repr": "2022-10-03 21:10:26.142185+03:00", "timestamp": 1664820626.142185}}}
